setup.py
BinomGauss/Binomialdistribution.py
BinomGauss/Gaussiandistribution.py
BinomGauss/Generaldistribution.py
BinomGauss/__init__.py
BinomGauss.egg-info/PKG-INFO
BinomGauss.egg-info/SOURCES.txt
BinomGauss.egg-info/dependency_links.txt
BinomGauss.egg-info/not-zip-safe
BinomGauss.egg-info/top_level.txt