Metadata-Version: 1.0
Name: BinomGauss
Version: 0.1
Summary: Gaussian and Binomial distributions
Home-page: UNKNOWN
Author: Soham Pendurkar
Author-email: UNKNOWN
License: UNKNOWN
Platform: UNKNOWN
